msal/__init__.py
msal/__main__.py
msal/application.py
msal/auth_scheme.py
msal/authority.py
msal/broker.py
msal/cloudshell.py
msal/exceptions.py
msal/individual_cache.py
msal/managed_identity.py
msal/mex.py
msal/region.py
msal/sku.py
msal/telemetry.py
msal/throttled_http_client.py
msal/token_cache.py
msal/wstrust_request.py
msal/wstrust_response.py
msal/oauth2cli/__init__.py
msal/oauth2cli/assertion.py
msal/oauth2cli/authcode.py
msal/oauth2cli/http.py
msal/oauth2cli/oauth2.py
msal/oauth2cli/oidc.py
msal-1.32.2.dist-info/licenses/LICENSE
msal-1.32.2.dist-info/METADATA
msal-1.32.2.dist-info/WHEEL
msal-1.32.2.dist-info/top_level.txt
msal-1.32.2.dist-info/RECORD
