Metadata-Version: 2.4
Name: msal
Version: 1.32.2
Summary: The Microsoft Authentication Library (MSAL) for Python library enables your app to access the Microsoft Cloud by supporting authentication of users with Microsoft Azure Active Directory accounts (AAD) and Microsoft Accounts (MSA) using industry standard OAuth2 and OpenID Connect.
Home-page: https://github.com/AzureAD/microsoft-authentication-library-for-python
Author: Microsoft Corporation
Author-email: nugetaad@microsoft.com
License: MIT
Project-URL: Changelog, https://github.com/AzureAD/microsoft-authentication-library-for-python/releases
Project-URL: Documentation, https://msal-python.readthedocs.io/
Project-URL: Questions, https://stackoverflow.com/questions/tagged/azure-ad-msal+python
Project-URL: Feature/Bug Tracker, https://github.com/AzureAD/microsoft-authentication-library-for-python/issues
Classifier: Development Status :: 5 - Production/Stable
Classifier: Programming Language :: Python
Classifier: Programming Language :: Python :: 3 :: Only
Classifier: Programming Language :: Python :: 3
Classifier: Programming Language :: Python :: 3.7
Classifier: Programming Language :: Python :: 3.8
Classifier: Programming Language :: Python :: 3.9
Classifier: Programming Language :: Python :: 3.10
Classifier: Programming Language :: Python :: 3.11
Classifier: Programming Language :: Python :: 3.12
Classifier: License :: OSI Approved :: MIT License
Classifier: Operating System :: OS Independent
Requires-Python: >=3.7
License-File: LICENSE
Requires-Dist: requests<3,>=2.0.0
Requires-Dist: PyJWT[crypto]<3,>=1.0.0
Requires-Dist: cryptography<47,>=2.5
Provides-Extra: broker
Requires-Dist: pymsalruntime<0.18,>=0.14; (python_version >= "3.6" and platform_system == "Windows") and extra == "broker"
Requires-Dist: pymsalruntime<0.18,>=0.17; (python_version >= "3.8" and platform_system == "Darwin") and extra == "broker"
Dynamic: license-file
